MfcChengxuyuanDeWtlZhinan/README.md
MfcChengxuyuanDeWtlZhinan/__init__.py
MfcChengxuyuanDeWtlZhinan/__main__.py
MfcChengxuyuanDeWtlZhinan/file.epub
MfcChengxuyuanDeWtlZhinan/index.html
MfcChengxuyuanDeWtlZhinan/css/__init__.py
MfcChengxuyuanDeWtlZhinan/css/annotations.css
MfcChengxuyuanDeWtlZhinan/css/main.css
MfcChengxuyuanDeWtlZhinan/css/normalize.css
MfcChengxuyuanDeWtlZhinan/css/popup.css
MfcChengxuyuanDeWtlZhinan/font/__init__.py
MfcChengxuyuanDeWtlZhinan/font/fontello.eot
MfcChengxuyuanDeWtlZhinan/font/fontello.svg
MfcChengxuyuanDeWtlZhinan/font/fontello.ttf
MfcChengxuyuanDeWtlZhinan/font/fontello.woff
MfcChengxuyuanDeWtlZhinan/img/__init__.py
MfcChengxuyuanDeWtlZhinan/img/annotator-glyph-sprite.png
MfcChengxuyuanDeWtlZhinan/img/annotator-icon-sprite.png
MfcChengxuyuanDeWtlZhinan/img/apple-touch-icon.png
MfcChengxuyuanDeWtlZhinan/img/cancelfullscreen.png
MfcChengxuyuanDeWtlZhinan/img/close.png
MfcChengxuyuanDeWtlZhinan/img/fullscreen.png
MfcChengxuyuanDeWtlZhinan/img/loader.gif
MfcChengxuyuanDeWtlZhinan/img/menu-icon.png
MfcChengxuyuanDeWtlZhinan/img/save.png
MfcChengxuyuanDeWtlZhinan/img/saved.png
MfcChengxuyuanDeWtlZhinan/img/settings-s.png
MfcChengxuyuanDeWtlZhinan/img/settings.png
MfcChengxuyuanDeWtlZhinan/img/star.png
MfcChengxuyuanDeWtlZhinan/js/__init__.py
MfcChengxuyuanDeWtlZhinan/js/epub.js
MfcChengxuyuanDeWtlZhinan/js/epub.min.js
MfcChengxuyuanDeWtlZhinan/js/epub.min.map
MfcChengxuyuanDeWtlZhinan/js/hooks.min.js
MfcChengxuyuanDeWtlZhinan/js/hooks.min.map
MfcChengxuyuanDeWtlZhinan/js/reader.js
MfcChengxuyuanDeWtlZhinan/js/reader.js.map
MfcChengxuyuanDeWtlZhinan/js/reader.min.js
MfcChengxuyuanDeWtlZhinan/js/reader.min.map
MfcChengxuyuanDeWtlZhinan/js/hooks/__init__.py
MfcChengxuyuanDeWtlZhinan/js/hooks/extensions/__init__.py
MfcChengxuyuanDeWtlZhinan/js/hooks/extensions/highlight.js
MfcChengxuyuanDeWtlZhinan/js/libs/__init__.py
MfcChengxuyuanDeWtlZhinan/js/libs/jquery.min.js
MfcChengxuyuanDeWtlZhinan/js/libs/localforage.min.js
mfc_chengxuyuan_de_wtl_zhinan-2024.2.29.0.dist-info/METADATA
mfc_chengxuyuan_de_wtl_zhinan-2024.2.29.0.dist-info/WHEEL
mfc_chengxuyuan_de_wtl_zhinan-2024.2.29.0.dist-info/entry_points.txt
mfc_chengxuyuan_de_wtl_zhinan-2024.2.29.0.dist-info/top_level.txt
mfc_chengxuyuan_de_wtl_zhinan-2024.2.29.0.dist-info/RECORD
